root_report/Report.py
root_report/__init__.py
root_report-0.1.7.dist-info/LICENSE
root_report-0.1.7.dist-info/METADATA
root_report-0.1.7.dist-info/WHEEL
root_report-0.1.7.dist-info/top_level.txt
root_report-0.1.7.dist-info/RECORD
