Metadata-Version: 2.1
Name: root-report
Version: 0.1.7
Summary: Simple package to produce HTML reports out of PyROOT scripts
Home-page: https://github.com/landerlini/root_report
Author: Lucio Anderlini
Author-email: l.anderlini@gmail.com
License: UNKNOWN
Platform: UNKNOWN
Classifier: Programming Language :: Python :: 2.7
Classifier: Programming Language :: Python :: 3.4
Classifier: Programming Language :: Python :: 3.5
Classifier: Programming Language :: Python :: 3.6
Classifier: Programming Language :: Python :: 3.7
Classifier: License :: OSI Approved :: GNU Lesser General Public License v2 or later (LGPLv2+)
Classifier: Operating System :: OS Independent
